pyprofilerai/__init__.py
pyprofilerai/profiler.py
pyprofilerai-0.1.3.dist-info/licenses/LICENSE
pyprofilerai-0.1.3.dist-info/METADATA
pyprofilerai-0.1.3.dist-info/WHEEL
pyprofilerai-0.1.3.dist-info/top_level.txt
pyprofilerai-0.1.3.dist-info/RECORD
