Metadata-Version: 2.4
Name: pyprofilerai
Version: 0.1.3
Summary: A python profiling tool with AI-based suggestions for performance optimization
Home-page: https://github.com/Ranuja01/pyprofilerai
Author: Ranuja Pinnaduwage
Author-email: Ranuja.Pinnaduwage@gmail.com
Classifier: Programming Language :: Python :: 3
Classifier: License :: OSI Approved :: MIT License
Classifier: Operating System :: OS Independent
Classifier: Intended Audience :: Developers
Classifier: Topic :: Scientific/Engineering
Classifier: Topic :: Scientific/Engineering :: Artificial Intelligence
Requires-Python: >=3.8
License-File: LICENSE
Requires-Dist: google-genai
Dynamic: author
Dynamic: author-email
Dynamic: classifier
Dynamic: description
Dynamic: description-content-type
Dynamic: home-page
Dynamic: license-file
Dynamic: requires-dist
Dynamic: requires-python
Dynamic: summary
